kdpy/__init__.py
kdpy/timer.py
kdpy-0.1.0.dist-info/LICENSE
kdpy-0.1.0.dist-info/METADATA
kdpy-0.1.0.dist-info/WHEEL
kdpy-0.1.0.dist-info/top_level.txt
kdpy-0.1.0.dist-info/RECORD
