Metadata-Version: 2.2
Name: kdpy
Version: 0.1.0
Summary: A Python utility library for developers
Author: Kaushal Tarpara
Author-email: kaushaltarpara10702@gmail.com
Classifier: Programming Language :: Python :: 3
Classifier: License :: OSI Approved :: MIT License
Classifier: Operating System :: OS Independent
Requires-Python: >=3.6
License-File: LICENSE
Dynamic: author
Dynamic: author-email
Dynamic: classifier
Dynamic: requires-python
Dynamic: summary
